hydra_openapi_parser/__init__.py
hydra_openapi_parser/openapi_parser.py
tests/__init__.py
tests/test_parser.py
hydra_openapi_parser-0.2.0.dist-info/LICENSE
hydra_openapi_parser-0.2.0.dist-info/METADATA
hydra_openapi_parser-0.2.0.dist-info/WHEEL
hydra_openapi_parser-0.2.0.dist-info/top_level.txt
hydra_openapi_parser-0.2.0.dist-info/RECORD
