Metadata-Version: 2.1
Name: hydra-openapi-parser
Version: 0.2.0
Summary: A Parser from OpenAPI to Hydra specs
Home-page: https://github.com/HTTP-APIs/hydra-openapi-parser
License: MIT
Platform: UNKNOWN
